{
  "schema_version": "animal-project-sample-site-review.v1",
  "rows": [
    {
      "project_accession": "PRJEB22390",
      "species_latin_name": "Equus caballus",
      "recovered_sample_row_count": 42,
      "direct_sample_site_count": 42,
      "sample_group_site_count": 0,
      "project_level_site_only_count": 0,
      "named_place_inferred_count": 0,
      "region_only_count": 0,
      "unresolved_count": 0,
      "lacking_defensible_site_assignment_count": 0,
      "missing_reasons": []
    },
    {
      "project_accession": "PRJEB44430",
      "species_latin_name": "Equus caballus",
      "recovered_sample_row_count": 248,
      "direct_sample_site_count": 248,
      "sample_group_site_count": 0,
      "project_level_site_only_count": 0,
      "named_place_inferred_count": 0,
      "region_only_count": 0,
      "unresolved_count": 0,
      "lacking_defensible_site_assignment_count": 0,
      "missing_reasons": []
    },
    {
      "project_accession": "PRJEB31613",
      "species_latin_name": "Equus caballus",
      "recovered_sample_row_count": 244,
      "direct_sample_site_count": 244,
      "sample_group_site_count": 0,
      "project_level_site_only_count": 0,
      "named_place_inferred_count": 0,
      "region_only_count": 0,
      "unresolved_count": 0,
      "lacking_defensible_site_assignment_count": 0,
      "missing_reasons": []
    },
    {
      "project_accession": "PRJEB19970",
      "species_latin_name": "Equus caballus",
      "recovered_sample_row_count": 14,
      "direct_sample_site_count": 14,
      "sample_group_site_count": 0,
      "project_level_site_only_count": 0,
      "named_place_inferred_count": 0,
      "region_only_count": 0,
      "unresolved_count": 0,
      "lacking_defensible_site_assignment_count": 0,
      "missing_reasons": []
    },
    {
      "project_accession": "PRJEB56293",
      "species_latin_name": "Equus caballus",
      "recovered_sample_row_count": 0,
      "direct_sample_site_count": 0,
      "sample_group_site_count": 0,
      "project_level_site_only_count": 0,
      "named_place_inferred_count": 0,
      "region_only_count": 0,
      "unresolved_count": 0,
      "lacking_defensible_site_assignment_count": 0,
      "missing_reasons": []
    },
    {
      "project_accession": "PRJEB7537",
      "species_latin_name": "Equus caballus",
      "recovered_sample_row_count": 0,
      "direct_sample_site_count": 0,
      "sample_group_site_count": 0,
      "project_level_site_only_count": 0,
      "named_place_inferred_count": 0,
      "region_only_count": 0,
      "unresolved_count": 0,
      "lacking_defensible_site_assignment_count": 0,
      "missing_reasons": []
    },
    {
      "project_accession": "PRJEB10854",
      "species_latin_name": "Equus caballus",
      "recovered_sample_row_count": 0,
      "direct_sample_site_count": 0,
      "sample_group_site_count": 0,
      "project_level_site_only_count": 0,
      "named_place_inferred_count": 0,
      "region_only_count": 0,
      "unresolved_count": 0,
      "lacking_defensible_site_assignment_count": 0,
      "missing_reasons": []
    },
    {
      "project_accession": "PRJEB9799",
      "species_latin_name": "Equus caballus",
      "recovered_sample_row_count": 0,
      "direct_sample_site_count": 0,
      "sample_group_site_count": 0,
      "project_level_site_only_count": 0,
      "named_place_inferred_count": 0,
      "region_only_count": 0,
      "unresolved_count": 0,
      "lacking_defensible_site_assignment_count": 0,
      "missing_reasons": []
    },
    {
      "project_accession": "PRJEB36540",
      "species_latin_name": "Ovis aries",
      "recovered_sample_row_count": 190,
      "direct_sample_site_count": 190,
      "sample_group_site_count": 0,
      "project_level_site_only_count": 0,
      "named_place_inferred_count": 0,
      "region_only_count": 0,
      "unresolved_count": 0,
      "lacking_defensible_site_assignment_count": 0,
      "missing_reasons": []
    },
    {
      "project_accession": "PRJEB41594",
      "species_latin_name": "Ovis aries",
      "recovered_sample_row_count": 0,
      "direct_sample_site_count": 0,
      "sample_group_site_count": 0,
      "project_level_site_only_count": 0,
      "named_place_inferred_count": 0,
      "region_only_count": 0,
      "unresolved_count": 0,
      "lacking_defensible_site_assignment_count": 0,
      "missing_reasons": []
    },
    {
      "project_accession": "PRJEB59481",
      "species_latin_name": "Ovis aries",
      "recovered_sample_row_count": 0,
      "direct_sample_site_count": 0,
      "sample_group_site_count": 0,
      "project_level_site_only_count": 0,
      "named_place_inferred_count": 0,
      "region_only_count": 0,
      "unresolved_count": 0,
      "lacking_defensible_site_assignment_count": 0,
      "missing_reasons": []
    },
    {
      "project_accession": "PRJEB61808",
      "species_latin_name": "Ovis aries",
      "recovered_sample_row_count": 0,
      "direct_sample_site_count": 0,
      "sample_group_site_count": 0,
      "project_level_site_only_count": 0,
      "named_place_inferred_count": 0,
      "region_only_count": 0,
      "unresolved_count": 0,
      "lacking_defensible_site_assignment_count": 0,
      "missing_reasons": []
    },
    {
      "project_accession": "PRJEB69690",
      "species_latin_name": "Ovis aries",
      "recovered_sample_row_count": 0,
      "direct_sample_site_count": 0,
      "sample_group_site_count": 0,
      "project_level_site_only_count": 0,
      "named_place_inferred_count": 0,
      "region_only_count": 0,
      "unresolved_count": 0,
      "lacking_defensible_site_assignment_count": 0,
      "missing_reasons": []
    },
    {
      "project_accession": "PRJEB81145",
      "species_latin_name": "Ovis aries",
      "recovered_sample_row_count": 0,
      "direct_sample_site_count": 0,
      "sample_group_site_count": 0,
      "project_level_site_only_count": 0,
      "named_place_inferred_count": 0,
      "region_only_count": 0,
      "unresolved_count": 0,
      "lacking_defensible_site_assignment_count": 0,
      "missing_reasons": []
    },
    {
      "project_accession": "PRJEB30282",
      "species_latin_name": "Sus scrofa domesticus",
      "recovered_sample_row_count": 0,
      "direct_sample_site_count": 0,
      "sample_group_site_count": 0,
      "project_level_site_only_count": 0,
      "named_place_inferred_count": 0,
      "region_only_count": 0,
      "unresolved_count": 0,
      "lacking_defensible_site_assignment_count": 0,
      "missing_reasons": []
    },
    {
      "project_accession": "PRJNA788987",
      "species_latin_name": "Sus scrofa domesticus",
      "recovered_sample_row_count": 0,
      "direct_sample_site_count": 0,
      "sample_group_site_count": 0,
      "project_level_site_only_count": 0,
      "named_place_inferred_count": 0,
      "region_only_count": 0,
      "unresolved_count": 0,
      "lacking_defensible_site_assignment_count": 0,
      "missing_reasons": []
    },
    {
      "project_accession": "PRJNA878488",
      "species_latin_name": "Sus scrofa domesticus",
      "recovered_sample_row_count": 0,
      "direct_sample_site_count": 0,
      "sample_group_site_count": 0,
      "project_level_site_only_count": 0,
      "named_place_inferred_count": 0,
      "region_only_count": 0,
      "unresolved_count": 0,
      "lacking_defensible_site_assignment_count": 0,
      "missing_reasons": []
    },
    {
      "project_accession": "PRJNA421430",
      "species_latin_name": "Sus scrofa domesticus",
      "recovered_sample_row_count": 0,
      "direct_sample_site_count": 0,
      "sample_group_site_count": 0,
      "project_level_site_only_count": 0,
      "named_place_inferred_count": 0,
      "region_only_count": 0,
      "unresolved_count": 0,
      "lacking_defensible_site_assignment_count": 0,
      "missing_reasons": []
    },
    {
      "project_accession": "PRJEB31621",
      "species_latin_name": "Bos taurus",
      "recovered_sample_row_count": 0,
      "direct_sample_site_count": 0,
      "sample_group_site_count": 0,
      "project_level_site_only_count": 0,
      "named_place_inferred_count": 0,
      "region_only_count": 0,
      "unresolved_count": 0,
      "lacking_defensible_site_assignment_count": 0,
      "missing_reasons": []
    },
    {
      "project_accession": "PRJEB75467",
      "species_latin_name": "Bos taurus",
      "recovered_sample_row_count": 0,
      "direct_sample_site_count": 0,
      "sample_group_site_count": 0,
      "project_level_site_only_count": 0,
      "named_place_inferred_count": 0,
      "region_only_count": 0,
      "unresolved_count": 0,
      "lacking_defensible_site_assignment_count": 0,
      "missing_reasons": []
    },
    {
      "project_accession": "PRJNA705960",
      "species_latin_name": "Bos taurus",
      "recovered_sample_row_count": 0,
      "direct_sample_site_count": 0,
      "sample_group_site_count": 0,
      "project_level_site_only_count": 0,
      "named_place_inferred_count": 0,
      "region_only_count": 0,
      "unresolved_count": 0,
      "lacking_defensible_site_assignment_count": 0,
      "missing_reasons": []
    },
    {
      "project_accession": "PRJEB90141",
      "species_latin_name": "Capra hircus",
      "recovered_sample_row_count": 0,
      "direct_sample_site_count": 0,
      "sample_group_site_count": 0,
      "project_level_site_only_count": 0,
      "named_place_inferred_count": 0,
      "region_only_count": 0,
      "unresolved_count": 0,
      "lacking_defensible_site_assignment_count": 0,
      "missing_reasons": []
    },
    {
      "project_accession": "PRJEB90261",
      "species_latin_name": "Capra hircus",
      "recovered_sample_row_count": 0,
      "direct_sample_site_count": 0,
      "sample_group_site_count": 0,
      "project_level_site_only_count": 0,
      "named_place_inferred_count": 0,
      "region_only_count": 0,
      "unresolved_count": 0,
      "lacking_defensible_site_assignment_count": 0,
      "missing_reasons": []
    },
    {
      "project_accession": "PRJNA1328209",
      "species_latin_name": "Capra hircus",
      "recovered_sample_row_count": 0,
      "direct_sample_site_count": 0,
      "sample_group_site_count": 0,
      "project_level_site_only_count": 0,
      "named_place_inferred_count": 0,
      "region_only_count": 0,
      "unresolved_count": 0,
      "lacking_defensible_site_assignment_count": 0,
      "missing_reasons": []
    },
    {
      "project_accession": "PRJEB81815",
      "species_latin_name": "Felis catus",
      "recovered_sample_row_count": 0,
      "direct_sample_site_count": 0,
      "sample_group_site_count": 0,
      "project_level_site_only_count": 0,
      "named_place_inferred_count": 0,
      "region_only_count": 0,
      "unresolved_count": 0,
      "lacking_defensible_site_assignment_count": 0,
      "missing_reasons": []
    },
    {
      "project_accession": "PRJNA1178732",
      "species_latin_name": "Felis catus",
      "recovered_sample_row_count": 0,
      "direct_sample_site_count": 0,
      "sample_group_site_count": 0,
      "project_level_site_only_count": 0,
      "named_place_inferred_count": 0,
      "region_only_count": 0,
      "unresolved_count": 0,
      "lacking_defensible_site_assignment_count": 0,
      "missing_reasons": []
    },
    {
      "project_accession": "SRS1407451",
      "species_latin_name": "Canis lupus familiaris",
      "recovered_sample_row_count": 1,
      "direct_sample_site_count": 0,
      "sample_group_site_count": 0,
      "project_level_site_only_count": 0,
      "named_place_inferred_count": 0,
      "region_only_count": 1,
      "unresolved_count": 0,
      "lacking_defensible_site_assignment_count": 1,
      "missing_reasons": [
        "region_only"
      ]
    },
    {
      "project_accession": "SRS1407453",
      "species_latin_name": "Canis lupus familiaris",
      "recovered_sample_row_count": 1,
      "direct_sample_site_count": 0,
      "sample_group_site_count": 0,
      "project_level_site_only_count": 0,
      "named_place_inferred_count": 0,
      "region_only_count": 0,
      "unresolved_count": 1,
      "lacking_defensible_site_assignment_count": 1,
      "missing_reasons": [
        "unresolved"
      ]
    },
    {
      "project_accession": "KX379528-KX379529",
      "species_latin_name": "Canis lupus familiaris",
      "recovered_sample_row_count": 2,
      "direct_sample_site_count": 0,
      "sample_group_site_count": 0,
      "project_level_site_only_count": 0,
      "named_place_inferred_count": 0,
      "region_only_count": 0,
      "unresolved_count": 2,
      "lacking_defensible_site_assignment_count": 2,
      "missing_reasons": [
        "unresolved"
      ]
    },
    {
      "project_accession": "SRP073444",
      "species_latin_name": "Camelus dromedarius",
      "recovered_sample_row_count": 0,
      "direct_sample_site_count": 0,
      "sample_group_site_count": 0,
      "project_level_site_only_count": 0,
      "named_place_inferred_count": 0,
      "region_only_count": 0,
      "unresolved_count": 0,
      "lacking_defensible_site_assignment_count": 0,
      "missing_reasons": []
    },
    {
      "project_accession": "KU605068-KU605080",
      "species_latin_name": "Camelus dromedarius",
      "recovered_sample_row_count": 13,
      "direct_sample_site_count": 0,
      "sample_group_site_count": 0,
      "project_level_site_only_count": 0,
      "named_place_inferred_count": 0,
      "region_only_count": 0,
      "unresolved_count": 13,
      "lacking_defensible_site_assignment_count": 13,
      "missing_reasons": [
        "unresolved"
      ]
    },
    {
      "project_accession": "PRJEB50952",
      "species_latin_name": "Equus asinus",
      "recovered_sample_row_count": 0,
      "direct_sample_site_count": 0,
      "sample_group_site_count": 0,
      "project_level_site_only_count": 0,
      "named_place_inferred_count": 0,
      "region_only_count": 0,
      "unresolved_count": 0,
      "lacking_defensible_site_assignment_count": 0,
      "missing_reasons": []
    },
    {
      "project_accession": "PRJEB52849",
      "species_latin_name": "Equus asinus",
      "recovered_sample_row_count": 0,
      "direct_sample_site_count": 0,
      "sample_group_site_count": 0,
      "project_level_site_only_count": 0,
      "named_place_inferred_count": 0,
      "region_only_count": 0,
      "unresolved_count": 0,
      "lacking_defensible_site_assignment_count": 0,
      "missing_reasons": []
    },
    {
      "project_accession": "PRJEB52590",
      "species_latin_name": "Equus asinus",
      "recovered_sample_row_count": 0,
      "direct_sample_site_count": 0,
      "sample_group_site_count": 0,
      "project_level_site_only_count": 0,
      "named_place_inferred_count": 0,
      "region_only_count": 0,
      "unresolved_count": 0,
      "lacking_defensible_site_assignment_count": 0,
      "missing_reasons": []
    },
    {
      "project_accession": "PRJEB43564",
      "species_latin_name": "Equus asinus",
      "recovered_sample_row_count": 0,
      "direct_sample_site_count": 0,
      "sample_group_site_count": 0,
      "project_level_site_only_count": 0,
      "named_place_inferred_count": 0,
      "region_only_count": 0,
      "unresolved_count": 0,
      "lacking_defensible_site_assignment_count": 0,
      "missing_reasons": []
    },
    {
      "project_accession": "PRJEB55549",
      "species_latin_name": "Equus asinus",
      "recovered_sample_row_count": 0,
      "direct_sample_site_count": 0,
      "sample_group_site_count": 0,
      "project_level_site_only_count": 0,
      "named_place_inferred_count": 0,
      "region_only_count": 0,
      "unresolved_count": 0,
      "lacking_defensible_site_assignment_count": 0,
      "missing_reasons": []
    },
    {
      "project_accession": "PRJEB60484",
      "species_latin_name": "Rangifer tarandus",
      "recovered_sample_row_count": 0,
      "direct_sample_site_count": 0,
      "sample_group_site_count": 0,
      "project_level_site_only_count": 0,
      "named_place_inferred_count": 0,
      "region_only_count": 0,
      "unresolved_count": 0,
      "lacking_defensible_site_assignment_count": 0,
      "missing_reasons": []
    },
    {
      "project_accession": "PRJEB57293",
      "species_latin_name": "Rangifer tarandus",
      "recovered_sample_row_count": 0,
      "direct_sample_site_count": 0,
      "sample_group_site_count": 0,
      "project_level_site_only_count": 0,
      "named_place_inferred_count": 0,
      "region_only_count": 0,
      "unresolved_count": 0,
      "lacking_defensible_site_assignment_count": 0,
      "missing_reasons": []
    },
    {
      "project_accession": "PRJEB61721",
      "species_latin_name": "Rangifer tarandus",
      "recovered_sample_row_count": 0,
      "direct_sample_site_count": 0,
      "sample_group_site_count": 0,
      "project_level_site_only_count": 0,
      "named_place_inferred_count": 0,
      "region_only_count": 0,
      "unresolved_count": 0,
      "lacking_defensible_site_assignment_count": 0,
      "missing_reasons": []
    },
    {
      "project_accession": "PRJNA634908",
      "species_latin_name": "Rangifer tarandus",
      "recovered_sample_row_count": 0,
      "direct_sample_site_count": 0,
      "sample_group_site_count": 0,
      "project_level_site_only_count": 0,
      "named_place_inferred_count": 0,
      "region_only_count": 0,
      "unresolved_count": 0,
      "lacking_defensible_site_assignment_count": 0,
      "missing_reasons": []
    }
  ]
}